<?xml version="1.0" encoding="utf-8"?>
<PanelName>SAMSUNG S6E3FAC</PanelName>
<PanelDescription>samsung cmd mode dsi panel(1080*2120 24bpp)</PanelDescription>
<Group id="Active Timing">
 <HorizontalActive>1080</HorizontalActive>
 <HorizontalFrontPorch>112</HorizontalFrontPorch>
 <HorizontalBackPorch>88</HorizontalBackPorch>
 <HorizontalSyncPulse>64</HorizontalSyncPulse>
 <VerticalActive>2120</VerticalActive>
 <VerticalFrontPorch>120</VerticalFrontPorch>
 <VerticalBackPorch>116</VerticalBackPorch>
 <VerticalSyncPulse>116</VerticalSyncPulse>
</Group>
<Group id="Display Interface">
 <InterfaceType>9</InterfaceType>
 <InterfaceColorFormat>3</InterfaceColorFormat>
</Group>
<Group id="DSI Interface">
 <DSIChannelId>2</DSIChannelId>
 <DSIVirtualId>0</DSIVirtualId>
 <DSIColorFormat>36</DSIColorFormat>
 <DSITrafficMode>2</DSITrafficMode>
 <DSILanes>4</DSILanes>
 <DSITEvSyncSelect>1</DSITEvSyncSelect>
 <DSITEUsingDedicatedTEPin>False</DSITEUsingDedicatedTEPin>
 <DSIRefreshRate>0x780000</DSIRefreshRate>
 <DSIEnableAutoRefresh>True</DSIEnableAutoRefresh>
 <DSIAutoRefreshFrameNumDiv>1</DSIAutoRefreshFrameNumDiv>
 <DSIInitMasterTime units='integer'>32</DSIInitMasterTime>
 <DSILP11AtInit units='Bool'>0</DSILP11AtInit>
 <DSITECheckEnable>True</DSITECheckEnable>
 <DSITEUsingDedicatedTEPin>True</DSITEUsingDedicatedTEPin>
 <DSITEvSyncStartPos>2120</DSITEvSyncStartPos>
 <DSITEvSyncInitVal>2120</DSITEvSyncInitVal>
 <DSIBitClockFrequency>1110000000</DSIBitClockFrequency>
 <DSIDSCEnable>True</DSIDSCEnable>
 <DSIDSCMajor>1</DSIDSCMajor>
 <DSIDSCMinor>1</DSIDSCMinor>
 <DSIDSCScr>0</DSIDSCScr>
 <DSIDSCProfileID>7</DSIDSCProfileID>
 <DSIDSCSliceWidth>540</DSIDSCSliceWidth>
 <DSIDSCSliceHeight>40</DSIDSCSliceHeight>
 <!--DisplayPrimaryFlags>0x01000000</DisplayPrimaryFlags-->
 <DSIControllerMapping>
  01
 </DSIControllerMapping>
</Group>
<DSIInitSequence>
 39 9D 01
 39 9E 11 00 00 89 30 80 08 48 04 38 00 28 02 1C 02 1C 02 00 02 3B 00 20 03 92 00 07 00 0E 02 E0 02 8B 18 00 10 F0 03 0C 20 00 06 0B 0B 33 0E 1C 2A 38 46 54 62 69 70 77 79 7B 7D 7E 01 02 01 00 09 40 09 BE 19 FC 19 FA 19 F8 1A 38 1A 78 1A B6 2A B6 2A F4 2A F4 4B 34 63 74 00

 05 11
 FF 78

 15 35 00

 39 2A 00 00 04 37
 39 2B 00 00 08 47

 39 F0 5A 5A
 39 60 00
 39 F7 0F
 39 F0 A5 A5

 39 F0 5A 5A
 15 53 20
 15 F7 0F
 39 F0 A5 A5

 39 F0 5A 5A
 39 B0 02 79 92
 39 92 27
 39 B0 02 88 92
 39 92 05 06 05 17 19 16 1F 21 1E 25 27 24 27 2A 26
 39 B0 03 61 92
 39 92 E2 09 09 09 92 1D 98 80 76 5E 5B 49 FF 90 00 00 01
 39 F0 A5 A5

 05 29
</DSIInitSequence>
<DSITermSequence>
 05 28
 FF 14
 05 10
 FF 78
</DSITermSequence>
<Group id='Backlight Configuration'>
 <BacklightType>3</BacklightType>
 <BacklightBitWidth>10</BacklightBitWidth>
 <BacklightDefault units='Percentage'>39</BacklightDefault>
 <BacklightPmicControlType>0</BacklightPmicControlType>
 <DisplayResetInfo>0 2000 5000 5000 0</DisplayResetInfo>
</Group>


